t2v_metrics/__init__.py
t2v_metrics/clipscore.py
t2v_metrics/constants.py
t2v_metrics/itmscore.py
t2v_metrics/score.py
t2v_metrics/vqascore.py
t2v_metrics/models/__init__.py
t2v_metrics/models/model.py
t2v_metrics/models/video_utils.py
t2v_metrics/models/clipscore_models/__init__.py
t2v_metrics/models/clipscore_models/blip2_itc_model.py
t2v_metrics/models/clipscore_models/clip_model.py
t2v_metrics/models/clipscore_models/hpsv2_model.py
t2v_metrics/models/clipscore_models/internvideo2_clip_model.py
t2v_metrics/models/clipscore_models/languagebind_video_clip_model.py
t2v_metrics/models/clipscore_models/pickscore_model.py
t2v_metrics/models/clipscore_models/umt_clip_model.py
t2v_metrics/models/clipscore_models/internvideo2/__init__.py
t2v_metrics/models/clipscore_models/internvideo2/configs.py
t2v_metrics/models/clipscore_models/internvideo2/internvideo2.py
t2v_metrics/models/clipscore_models/internvideo2/multi_modality/__init__.py
t2v_metrics/models/clipscore_models/internvideo2/multi_modality/demo_config.py
t2v_metrics/models/clipscore_models/internvideo2/multi_modality/configs/config_bert.json
t2v_metrics/models/clipscore_models/internvideo2/multi_modality/configs/config_bert_large.json
t2v_metrics/models/clipscore_models/internvideo2/multi_modality/configs/data.py
t2v_metrics/models/clipscore_models/internvideo2/multi_modality/configs/med_config.json
t2v_metrics/models/clipscore_models/internvideo2/multi_modality/configs/med_config_fusion.json
t2v_metrics/models/clipscore_models/internvideo2/multi_modality/configs/med_large_config.json
t2v_metrics/models/clipscore_models/internvideo2/multi_modality/configs/model.py
t2v_metrics/models/clipscore_models/internvideo2/multi_modality/dataset/__init__.py
t2v_metrics/models/clipscore_models/internvideo2/multi_modality/dataset/av_utils.py
t2v_metrics/models/clipscore_models/internvideo2/multi_modality/dataset/base_dataset.py
t2v_metrics/models/clipscore_models/internvideo2/multi_modality/dataset/dataloader.py
t2v_metrics-3.0.dist-info/licenses/LICENSE
t2v_metrics-3.0.dist-info/METADATA
t2v_metrics-3.0.dist-info/WHEEL
t2v_metrics-3.0.dist-info/top_level.txt
t2v_metrics-3.0.dist-info/RECORD
