Metadata-Version: 2.4
Name: t2v_metrics
Version: 3.0
Summary: Evaluating Text-to-Visual Generation with Image-to-Text Generation.
Author-email: Zhiqiu Lin <zl279@cornell.edu>, Chancharik Mitra <chancharikm@gmail.com>
Project-URL: Home, https://linzhiqiu.github.io/papers/vqascore
Classifier: Programming Language :: Python :: 3
Classifier: License :: OSI Approved :: Apache Software License
Requires-Python: >=3.10
License-File: LICENSE
Requires-Dist: torch==2.5.1
Requires-Dist: torchvision==0.20.1
Requires-Dist: torchaudio==2.5.1
Requires-Dist: xformers
Requires-Dist: ftfy>=6.1.1
Requires-Dist: tqdm>=4.64.1
Requires-Dist: gdown>=4.7.1
Requires-Dist: huggingface-hub>=0.19.4
Requires-Dist: matplotlib>=3.6.2
Requires-Dist: numpy==1.26.4
Requires-Dist: open-clip-torch>=2.23.0
Requires-Dist: openai
Requires-Dist: opencv-python>=4.11.0.86
Requires-Dist: opencv-python-headless
Requires-Dist: pandas>=2.1.4
Requires-Dist: scipy>=1.11.4
Requires-Dist: sentencepiece>=0.1.99
Requires-Dist: transformers==4.49.0
Requires-Dist: datasets>=2.15.0
Requires-Dist: tokenizers
Requires-Dist: omegaconf
Requires-Dist: iopath
Requires-Dist: fairscale
Requires-Dist: scikit-learn
Requires-Dist: pycocoevalcap
Requires-Dist: hpsv2
Requires-Dist: fire==0.4.0
Requires-Dist: tiktoken>=0.7.0
Requires-Dist: peft==0.5.0
Requires-Dist: matplotlib-inline
Requires-Dist: decord
Requires-Dist: easydict
Requires-Dist: protobuf
Requires-Dist: pytz
Requires-Dist: av
Requires-Dist: icecream
Requires-Dist: markdown2
Requires-Dist: pydantic
Requires-Dist: accelerate
Requires-Dist: shortuuid
Requires-Dist: bitsandbytes
Requires-Dist: requests
Requires-Dist: httpx==0.24.0
Requires-Dist: uvicorn
Requires-Dist: einops-exts
Requires-Dist: einops
Requires-Dist: PyYAML
Requires-Dist: wandb
Requires-Dist: torchcodec==0.1
Requires-Dist: moviepy
Requires-Dist: apex==0.9.10dev
Requires-Dist: deepspeed
Requires-Dist: fvcore==0.1.5.post20221221
Requires-Dist: imageio==2.31.1
Requires-Dist: librosa==0.10.1
Requires-Dist: Pillow==10.0.0
Requires-Dist: psutil==5.9.5
Requires-Dist: soundfile==0.12.1
Requires-Dist: termcolor==2.4.0
Requires-Dist: qwen-vl-utils
Requires-Dist: func_timeout
Requires-Dist: timm>=1.0.15
Requires-Dist: torch>=2.3.1
Requires-Dist: gitpython
Requires-Dist: torchvision>=0.18.1
Requires-Dist: torchaudio>=2.3.1
Requires-Dist: google-genai
Requires-Dist: blobfile
Requires-Dist: diffusers
Requires-Dist: nltk
Requires-Dist: rouge-score
Dynamic: license-file
